cookietemple/__init__.py
cookietemple/__main__.py
cookietemple/bump_version/__init__.py
cookietemple/bump_version/bump_version.py
cookietemple/common/__init__.py
cookietemple/common/levensthein_dist.py
cookietemple/common/load_yaml.py
cookietemple/common/suggest_similar_commands.py
cookietemple/common/version.py
cookietemple/config/__init__.py
cookietemple/config/config.py
cookietemple/create/__init__.py
cookietemple/create/create.py
cookietemple/create/domains/__init__.py
cookietemple/create/domains/cli_creator.py
cookietemple/create/domains/cookietemple_template_struct.py
cookietemple/create/domains/gui_creator.py
cookietemple/create/domains/lib_creator.py
cookietemple/create/domains/pub_creator.py
cookietemple/create/domains/web_creator.py
cookietemple/create/github_support.py
cookietemple/create/template_creator.py
cookietemple/create/templates/__init__.py
cookietemple/create/templates/available_templates.yml
cookietemple/create/templates/cli/cli_java/cookiecutter.json
cookietemple/create/templates/cli/cli_java/{{ cookiecutter.project_slug }}/.gitattributes
cookietemple/create/templates/cli/cli_java/{{ cookiecutter.project_slug }}/.github/dependabot.yml
cookietemple/create/templates/cli/cli_java/{{ cookiecutter.project_slug }}/.github/workflows/build_deploy.yml
cookietemple/create/templates/cli/cli_java/{{ cookiecutter.project_slug }}/.github/workflows/run_checkstyle.yml
cookietemple/create/templates/cli/cli_java/{{ cookiecutter.project_slug }}/.github/workflows/run_tests.yml
cookietemple/create/templates/cli/cli_java/{{ cookiecutter.project_slug }}/.project
cookietemple/create/templates/cli/cli_java/{{ cookiecutter.project_slug }}/.settings/org.eclipse.buildship.core.prefs
cookietemple/create/templates/cli/cli_java/{{ cookiecutter.project_slug }}/Dockerfile
cookietemple/create/templates/cli/cli_java/{{ cookiecutter.project_slug }}/Makefile
cookietemple/create/templates/cli/cli_java/{{ cookiecutter.project_slug }}/README.rst
cookietemple-1.4.1.dist-info/entry_points.txt
cookietemple-1.4.1.dist-info/LICENSE
cookietemple-1.4.1.dist-info/WHEEL
cookietemple-1.4.1.dist-info/METADATA
cookietemple-1.4.1.dist-info/RECORD
