Metadata-Version: 2.1
Name: cookietemple
Version: 1.4.1
Summary: A cookiecutter based project template creation tool supporting several domains and languages with advanced linting, syncing and standardized workflows to get your project kickstarted in no time.
Home-page: https://cookietemple.com
License: Apache2.0
Author: Philipp Ehmele
Author-email: philipp_ehm@protonmail.com
Requires-Python: >=3.6.1,<3.10
Classifier: License :: Other/Proprietary License
Classifier: Programming Language :: Python :: 3
Classifier: Programming Language :: Python :: 3.10
Classifier: Programming Language :: Python :: 3.7
Classifier: Programming Language :: Python :: 3.8
Classifier: Programming Language :: Python :: 3.9
Requires-Dist: GitPython (>=3.1.17,<4.0.0)
Requires-Dist: PyNaCl (==1.5.0)
Requires-Dist: appdirs (>=1.4.4,<2.0.0)
Requires-Dist: cffi (>=1.14.5,<2.0.0)
Requires-Dist: click (>=8.0.1,<9.0.0)
Requires-Dist: cookiecutter (>=1.7.2,<2.0.0)
Requires-Dist: cryptography (>=3.4.7,<37.0.0)
Requires-Dist: packaging (>=20.9,<22.0)
Requires-Dist: pygithub (>=1.54.1,<2.0.0)
Requires-Dist: pynacl (>=1.4.0,<2.0.0)
Requires-Dist: questionary (>=1.9.0,<2.0.0)
Requires-Dist: requests (>=2.25.1,<3.0.0)
Requires-Dist: rich (>=10.2.2,<11.0.0)
Requires-Dist: ruamel.yaml (>=0.17.4,<0.18.0)
Project-URL: Documentation, https://cookietemple.readthedocs.io
Project-URL: Repository, https://github.com/cookiejar/cookietemple
